keyness/__init__.py
keyness/main.py
Keyness-0.26.dist-info/LICENSE.txt
Keyness-0.26.dist-info/METADATA
Keyness-0.26.dist-info/WHEEL
Keyness-0.26.dist-info/top_level.txt
Keyness-0.26.dist-info/RECORD
