Metadata-Version: 2.1
Name: Keyness
Version: 0.26
Summary: Rank orders log likelihood values for every token or ngram in a corpus.
Home-page: https://github.com/mikesuhan/keyness
Author: Mike Suhan
Author-email: mikesuhan@gmail.com
License: MIT License
License-File: LICENSE.txt
